ffpiv/__init__.py
ffpiv/api.py
ffpiv/nb_utils.py
ffpiv/pfftw.py
ffpiv/pnb.py
ffpiv/pnp.py
ffpiv/sample_data.py
ffpiv/window.py
ffpiv-0.2.0.dist-info/licenses/LICENSE
ffpiv-0.2.0.dist-info/WHEEL
ffpiv-0.2.0.dist-info/METADATA
ffpiv-0.2.0.dist-info/RECORD
