Metadata-Version: 2.4
Name: ffpiv
Version: 0.2.0
Summary: FF-PIV: Fast and Flexible Particle Image Velocimetry analysis powered by numba.
Author-email: Hessel Winsemius <winsemius@rainbowsensing.com>
Requires-Python: >=3.9
Classifier: Development Status :: 4 - Beta
Classifier: Intended Audience :: Developers
Classifier: Intended Audience :: Science/Research
Classifier: Topic :: Scientific/Engineering :: Hydrology
Classifier: Topic :: Scientific/Engineering :: Image Processing
Classifier: License :: OSI Approved :: GNU Affero General Public License v3
Classifier: Programming Language :: Python :: 3
Classifier: Programming Language :: Python :: 3.9
Classifier: Programming Language :: Python :: 3.10
Classifier: Programming Language :: Python :: 3.11
Classifier: Programming Language :: Python :: 3.12
Classifier: Programming Language :: Python :: 3.13
Classifier: Programming Language :: Python :: 3.14
License-File: LICENSE
Requires-Dist: numba
Requires-Dist: numpy
Requires-Dist: pillow
Requires-Dist: pip
Requires-Dist: platformdirs
Requires-Dist: psutil
Requires-Dist: pyFFTW
Requires-Dist: rocket-fft; python_version <= '3.12'
Requires-Dist: matplotlib ; extra == "extra"
Requires-Dist: notebook ; extra == "extra"
Requires-Dist: pooch ; extra == "extra"
Requires-Dist: tqdm ; extra == "extra"
Requires-Dist: ffpiv[extra, test] ; extra == "full"
Requires-Dist: pooch ; extra == "test"
Requires-Dist: tqdm ; extra == "test"
Requires-Dist: pytest ; extra == "test"
Requires-Dist: pytest-cov ; extra == "test"
Project-URL: Source, https://github.com/localdevices/ffpiv
Provides-Extra: extra
Provides-Extra: full
Provides-Extra: test
